{"BOIX/J+2SWlG1S0uQlsHnw==":"dmr-elektromekanik.svg","WMgF3HR9cvKGXCBL7iWqbQ==":"logo-110x95.png","ifaDAYMMvI74ZlGdW8rWZA==":"gf-297x222.jpg","amFKrFsoihckp5aGjcbv8Q==":"faurecia-297x222.jpg","WDXH8Yngfcku7uv8m5a50w==":"sampa-297x222.jpg","1nAB1VeZ1TeSzOSky7tPSw==":"alpplas-297x222.jpg","ZiL5hhByG74QYdu5TlNGnA==":"takosan-297x222.jpg","wZp/QIKOTJU9InnCtV/NcA==":"poliza-297x222.jpg","cXmuN/8GJoUoC0m2eh+FPg==":"kastamonu_plastik-297x222.jpg","X/7Vs/ZhvID8yUOzIZ94pg==":"borled-297x222.jpg","Rldvd5O/app69vuCLacVbQ==":"plaskal-297x222.jpg","M3GTiyF9Of3KtpfCQeNyQQ==":"difas-297x222.jpg","D4Hd7X3O32M6jUdr5nkmPw==":"hobby-297x222.jpg","R7mIgsb1Jd/SLHmaqAuTGg==":"askapak-297x222.jpg","+NSum9Z/ews8ZfxhYEpDBQ==":"ak_komsan-297x222.jpg","+yUHR9uDJsIFj+beoOGN/Q==":"paprix-297x222.jpg","8ZfXsCxJvQUfv/GskNHKtA==":"pensan-297x222.jpg","zjm2InLQP83sP0Zc/zEK6Q==":"peksan-297x222.jpg","+g5kN0W01CwvqDhNJQuO6A==":"teknika_plast-297x222.jpg","+BZtWuNIzFGVnuNCrwewdg==":"plastik_isleme-159x119.jpg","kXqNPqodDx8mGa4MooUByw==":"plastik_isleme-457x343.jpg","EPhped/vS/5JIbJrOvmIHA==":"saglik-457x343.jpg","qxJeod05AVkOHV8hqgDU9w==":"tuketici_urunleri-457x343.jpg","+lH4bWfXXYO2Mpd8QqHZ5g==":"otomotiv-457x343.jpg","0/H/KWX68mDpEHsFYgU8VA==":"ambalaj-457x343.jpg","IN/8QC/c6d21iOenIDemJg==":"elektrik-457x343.jpg","mvkO6cPphikMEFgQFHxhDw==":"elektronik-1024x768.jpg","cJSkD/UJbjttN6R26mRlCg==":"yazilim-1024x768.jpg","WhZhNPkMagZKeRbIGC0DEw==":"whatsapp%2520image%25202025-12-17%2520at%252019.19.31-111x73.jpg","oSl2jqyXg577nh3GDrJo7g==":"whatsapp%2520image%25202025-12-17%2520at%252019.19.31-145x76.png","UKVNjNElg1ikIUPemEjh2w==":"injection-molding-machine-8-640x348.jpg","3i8CwNLh2ogRIumeD/ujyg==":"what-is-injection-molding.webp"}